onedatafilerestclient/__init__.py
onedatafilerestclient/errors.py
onedatafilerestclient/httpclient.py
onedatafilerestclient/main.py
onedatafilerestclient-21.2.5rc1.dist-info/LICENSE.txt
onedatafilerestclient-21.2.5rc1.dist-info/METADATA
onedatafilerestclient-21.2.5rc1.dist-info/WHEEL
onedatafilerestclient-21.2.5rc1.dist-info/top_level.txt
onedatafilerestclient-21.2.5rc1.dist-info/RECORD
